{"events": [{"timestamp": 8308615, "type": "applydebuff", "sourceID": 14, "sourceIsFriendly": true, "targetID": 55, "targetIsFriendly": false, "ability": {"name": "Curse of the Elements", "guid": 11722, "type": 32, "abilityIcon": "spell_shadow_chilltouch.jpg"}}, {"timestamp": 8309035, "type": "applydebuff", "sourceID": 15, "sourceIsFriendly": true, "targetID": 55, "targetIsFriendly": false, "ability": {"name": "Vampiric Embrace", "guid": 15286, "type": 32, "abilityIcon": "spell_shadow_unsummonbuilding.jpg"}}, {"timestamp": 8309035, "type": "applydebuff", "sourceID": 25, "sourceIsFriendly": true, "targetID": 55, "targetIsFriendly": false, "ability": {"name": "Corruption", "guid": 11672, "type": 32, "abilityIcon": "spell_shadow_abominationexplosion.jpg"}}, {"timestamp": 8309035, "type": "applydebuff", "sourceID": 27, "sourceIsFriendly": true, "targetID": 55, "targetIsFriendly": false, "ability": {"name": "Corruption", "guid": 11672, "type": 32, "abilityIcon": "spell_shadow_abominationexplosion.jpg"}}, {"timestamp": 8309842, "type": "applydebuff", "sourceID": 23, "sourceIsFriendly": true, "targetID": 55, "targetIsFriendly": false, "ability": {"name": "Curse of Shadow", "guid": 17937, "type": 32, "abilityIcon": "spell_shadow_curseofachimonde.jpg"}}, {"timestamp": 8309842, "type": "applydebuff", "sourceID": 14, "sourceIsFriendly": true, "targetID": 55, "targetIsFriendly": false, "ability": {"name": "Corruption", "guid": 11672, "type": 32, "abilityIcon": "spell_shadow_abominationexplosion.jpg"}}, {"timestamp": 8310243, "type": "applydebuff", "sourceID": 33, "sourceIsFriendly": true, "targetID": 55, "targetIsFriendly": false, "ability": {"name": "Sunder Armor", "guid": 11597, "type": 1, "abilityIcon": "ability_warrior_sunder.jpg"}}, {"timestamp": 8310243, "type": "applydebuff", "sourceID": 33, "sourceIsFriendly": true, "targetID": 55, "targetIsFriendly": false, "ability": {"name": "Taunt", "guid": 355, "type": 1, "abilityIcon": "spell_nature_reincarnation.jpg"}}, {"timestamp": 8310645, "type": "applydebuff", "sourceID": 15, "sourceIsFriendly": true, "targetID": 55, "targetIsFriendly": false, "ability": {"name": "Shadow Word: Pain", "guid": 10894, "type": 32, "abilityIcon": "spell_shadow_shadowwordpain.jpg"}}, {"timestamp": 8310645, "type": "applydebuff", "sourceID": 15, "sourceIsFriendly": true, "targetID": 55, "targetIsFriendly": false, "ability": {"name": "", "guid": 15258, "type": 32, "abilityIcon": "spell_shadow_blackplague.jpg"}}, {"timestamp": 8311060, "type": "applydebuff", "sourceID": 23, "sourceIsFriendly": true, "targetID": 55, "targetIsFriendly": false, "ability": {"name": "Corruption", "guid": 11672, "type": 32, "abilityIcon": "spell_shadow_abominationexplosion.jpg"}}, {"timestamp": 8311462, "type": "applydebuff", "sourceID": 27, "sourceIsFriendly": true, "targetID": 55, "targetIsFriendly": false, "ability": {"name": "Curse of Recklessness", "guid": 11717, "type": 32, "abilityIcon": "spell_shadow_unholystrength.jpg"}}, {"timestamp": 8311873, "type": "applydebuff", "sourceID": 15, "sourceIsFriendly": true, "targetID": 55, "targetIsFriendly": false, "ability": {"name": "Mind Flay", "guid": 18807, "type": 32, "abilityIcon": "spell_shadow_siphonmana.jpg"}}, {"timestamp": 8311873, "type": "applydebuffstack", "sourceID": 15, "sourceIsFriendly": true, "targetID": 55, "targetIsFriendly": false, "ability": {"name": "", "guid": 15258, "type": 32, "abilityIcon": "spell_shadow_blackplague.jpg"}, "stack": 2}, {"timestamp": 8312274, "type": "applydebuff", "sourceID": 7, "sourceIsFriendly": true, "targetID": 55, "targetIsFriendly": false, "ability": {"name": "", "guid": 12579, "type": 16, "abilityIcon": "spell_frost_chillingblast.jpg"}}, {"timestamp": 8312709, "type": "applydebuffstack", "sourceID": 33, "sourceIsFriendly": true, "targetID": 55, "targetIsFriendly": false, "ability": {"name": "Sunder Armor", "guid": 11597, "type": 1, "abilityIcon": "ability_warrior_sunder.jpg"}, "stack": 2}, {"timestamp": 8313240, "type": "removedebuff", "sourceID": 33, "sourceIsFriendly": true, "targetID": 55, "targetIsFriendly": false, "ability": {"name": "Taunt", "guid": 355, "type": 1, "abilityIcon": "spell_nature_reincarnation.jpg"}}, {"timestamp": 8313881, "type": "applydebuffstack", "sourceID": 7, "sourceIsFriendly": true, "targetID": 55, "targetIsFriendly": false, "ability": {"name": "", "guid": 12579, "type": 16, "abilityIcon": "spell_frost_chillingblast.jpg"}, "stack": 2}, {"timestamp": 8314286, "type": "applydebuff", "sourceID": 25, "sourceIsFriendly": true, "targetID": 55, "targetIsFriendly": false, "ability": {"name": "", "guid": 17800, "type": 32, "abilityIcon": "spell_shadow_shadowbolt.jpg"}}, {"timestamp": 8314873, "type": "removedebuff", "sourceID": 15, "sourceIsFriendly": true, "targetID": 55, "targetIsFriendly": false, "ability": {"name": "Mind Flay", "guid": 18807, "type": 32, "abilityIcon": "spell_shadow_siphonmana.jpg"}}, {"timestamp": 8315082, "type": "applydebuffstack", "sourceID": 7, "sourceIsFriendly": true, "targetID": 55, "targetIsFriendly": false, "ability": {"name": "", "guid": 12579, "type": 16, "abilityIcon": "spell_frost_chillingblast.jpg"}, "stack": 3}, {"timestamp": 8315194, "type": "removedebuffstack", "sourceID": 25, "sourceIsFriendly": true, "targetID": 55, "targetIsFriendly": false, "ability": {"name": "", "guid": 17800, "type": 32, "abilityIcon": "spell_shadow_shadowbolt.jpg"}, "stack": 3}, {"timestamp": 8316067, "type": "removedebuffstack", "sourceID": 25, "sourceIsFriendly": true, "targetID": 55, "targetIsFriendly": false, "ability": {"name": "", "guid": 17800, "type": 32, "abilityIcon": "spell_shadow_shadowbolt.jpg"}, "stack": 2}, {"timestamp": 8316167, "type": "removedebuffstack", "sourceID": 25, "sourceIsFriendly": true, "targetID": 55, "targetIsFriendly": false, "ability": {"name": "", "guid": 17800, "type": 32, "abilityIcon": "spell_shadow_shadowbolt.jpg"}, "stack": 1}, {"timestamp": 8316299, "type": "applydebuffstack", "sourceID": 7, "sourceIsFriendly": true, "targetID": 55, "targetIsFriendly": false, "ability": {"name": "", "guid": 12579, "type": 16, "abilityIcon": "spell_frost_chillingblast.jpg"}, "stack": 4}, {"timestamp": 8316419, "type": "removedebuff", "sourceID": 25, "sourceIsFriendly": true, "targetID": 55, "targetIsFriendly": false, "ability": {"name": "", "guid": 17800, "type": 32, "abilityIcon": "spell_shadow_shadowbolt.jpg"}}, {"timestamp": 8316711, "type": "applydebuff", "sourceID": 27, "sourceIsFriendly": true, "targetID": 55, "targetIsFriendly": false, "ability": {"name": "", "guid": 17800, "type": 32, "abilityIcon": "spell_shadow_shadowbolt.jpg"}}, {"timestamp": 8317525, "type": "applydebuffstack", "sourceID": 7, "sourceIsFriendly": true, "targetID": 55, "targetIsFriendly": false, "ability": {"name": "", "guid": 12579, "type": 16, "abilityIcon": "spell_frost_chillingblast.jpg"}, "stack": 5}, {"timestamp": 8318285, "type": "removedebuffstack", "sourceID": 27, "sourceIsFriendly": true, "targetID": 55, "targetIsFriendly": false, "ability": {"name": "", "guid": 17800, "type": 32, "abilityIcon": "spell_shadow_shadowbolt.jpg"}, "stack": 3}, {"timestamp": 8318327, "type": "applydebuff", "sourceID": 18, "sourceIsFriendly": true, "targetID": 55, "targetIsFriendly": false, "ability": {"name": "Moonfire", "guid": 9834, "type": 64, "abilityIcon": "spell_nature_starfall.jpg"}}, {"timestamp": 8318327, "type": "applydebuffstack", "sourceID": 33, "sourceIsFriendly": true, "targetID": 55, "targetIsFriendly": false, "ability": {"name": "Sunder Armor", "guid": 11597, "type": 1, "abilityIcon": "ability_warrior_sunder.jpg"}, "stack": 3}, {"timestamp": 8318622, "type": "removedebuffstack", "sourceID": 27, "sourceIsFriendly": true, "targetID": 55, "targetIsFriendly": false, "ability": {"name": "", "guid": 17800, "type": 32, "abilityIcon": "spell_shadow_shadowbolt.jpg"}, "stack": 2}, {"timestamp": 8319132, "type": "removedebuffstack", "sourceID": 27, "sourceIsFriendly": true, "targetID": 55, "targetIsFriendly": false, "ability": {"name": "", "guid": 17800, "type": 32, "abilityIcon": "spell_shadow_shadowbolt.jpg"}, "stack": 1}, {"timestamp": 8319942, "type": "removedebuff", "sourceID": 27, "sourceIsFriendly": true, "targetID": 55, "targetIsFriendly": false, "ability": {"name": "", "guid": 17800, "type": 32, "abilityIcon": "spell_shadow_shadowbolt.jpg"}}, {"timestamp": 8319942, "type": "applydebuffstack", "sourceID": 15, "sourceIsFriendly": true, "targetID": 55, "targetIsFriendly": false, "ability": {"name": "", "guid": 15258, "type": 32, "abilityIcon": "spell_shadow_blackplague.jpg"}, "stack": 3}, {"timestamp": 8320756, "type": "applydebuffstack", "sourceID": 33, "sourceIsFriendly": true, "targetID": 55, "targetIsFriendly": false, "ability": {"name": "Sunder Armor", "guid": 11597, "type": 1, "abilityIcon": "ability_warrior_sunder.jpg"}, "stack": 4}, {"timestamp": 8320756, "type": "applydebuffstack", "sourceID": 33, "sourceIsFriendly": true, "targetID": 55, "targetIsFriendly": false, "ability": {"name": "Sunder Armor", "guid": 11597, "type": 1, "abilityIcon": "ability_warrior_sunder.jpg"}, "stack": 5}, {"timestamp": 8321160, "type": "applydebuff", "sourceID": 15, "sourceIsFriendly": true, "targetID": 55, "targetIsFriendly": false, "ability": {"name": "Mind Flay", "guid": 18807, "type": 32, "abilityIcon": "spell_shadow_siphonmana.jpg"}}, {"timestamp": 8321160, "type": "applydebuffstack", "sourceID": 15, "sourceIsFriendly": true, "targetID": 55, "targetIsFriendly": false, "ability": {"name": "", "guid": 15258, "type": 32, "abilityIcon": "spell_shadow_blackplague.jpg"}, "stack": 4}, {"timestamp": 8322358, "type": "applydebuff", "sourceID": 33, "sourceIsFriendly": true, "targetID": 55, "targetIsFriendly": false, "ability": {"name": "Taunt", "guid": 355, "type": 1, "abilityIcon": "spell_nature_reincarnation.jpg"}}, {"timestamp": 8322369, "type": "applydebuff", "sourceID": 14, "sourceIsFriendly": true, "targetID": 55, "targetIsFriendly": false, "ability": {"name": "Shadowburn", "guid": 18871, "type": 32, "abilityIcon": "spell_shadow_scourgebuild.jpg"}}, {"timestamp": 8322769, "type": "removedebuff", "sourceID": 25, "sourceIsFriendly": true, "targetID": 55, "targetIsFriendly": false, "ability": {"name": "Corruption", "guid": 11672, "type": 32, "abilityIcon": "spell_shadow_abominationexplosion.jpg"}}, {"timestamp": 8322769, "type": "applydebuff", "sourceID": 32, "sourceIsFriendly": true, "targetID": 55, "targetIsFriendly": false, "ability": {"name": "Taunt", "guid": 355, "type": 1, "abilityIcon": "spell_nature_reincarnation.jpg"}}, {"timestamp": 8323589, "type": "removedebuff", "sourceID": 27, "sourceIsFriendly": true, "targetID": 55, "targetIsFriendly": false, "ability": {"name": "Corruption", "guid": 11672, "type": 32, "abilityIcon": "spell_shadow_abominationexplosion.jpg"}}, {"timestamp": 8323589, "type": "applydebuff", "sourceID": 27, "sourceIsFriendly": true, "targetID": 55, "targetIsFriendly": false, "ability": {"name": "Drain Soul", "guid": 11675, "type": 32, "abilityIcon": "spell_shadow_haunting.jpg"}}, {"timestamp": 8324155, "type": "removedebuff", "sourceID": 15, "sourceIsFriendly": true, "targetID": 55, "targetIsFriendly": false, "ability": {"name": "Mind Flay", "guid": 18807, "type": 32, "abilityIcon": "spell_shadow_siphonmana.jpg"}}, {"timestamp": 8324393, "type": "applydebuff", "sourceID": 15, "sourceIsFriendly": true, "targetID": 55, "targetIsFriendly": false, "ability": {"name": "Mind Flay", "guid": 18807, "type": 32, "abilityIcon": "spell_shadow_siphonmana.jpg"}}, {"timestamp": 8324393, "type": "applydebuffstack", "sourceID": 15, "sourceIsFriendly": true, "targetID": 55, "targetIsFriendly": false, "ability": {"name": "", "guid": 15258, "type": 32, "abilityIcon": "spell_shadow_blackplague.jpg"}, "stack": 5}, {"timestamp": 8324393, "type": "removedebuff", "sourceID": 14, "sourceIsFriendly": true, "targetID": 55, "targetIsFriendly": false, "ability": {"name": "Corruption", "guid": 11672, "type": 32, "abilityIcon": "spell_shadow_abominationexplosion.jpg"}}, {"timestamp": 8324393, "type": "applydebuff", "sourceID": 23, "sourceIsFriendly": true, "targetID": 55, "targetIsFriendly": false, "ability": {"name": "Drain Soul", "guid": 11675, "type": 32, "abilityIcon": "spell_shadow_haunting.jpg"}}, {"timestamp": 8325371, "type": "removedebuff", "sourceID": 33, "sourceIsFriendly": true, "targetID": 55, "targetIsFriendly": false, "ability": {"name": "Taunt", "guid": 355, "type": 1, "abilityIcon": "spell_nature_reincarnation.jpg"}}, {"timestamp": 8325604, "type": "applydebuff", "sourceID": 25, "sourceIsFriendly": true, "targetID": 55, "targetIsFriendly": false, "ability": {"name": "Drain Soul", "guid": 11675, "type": 32, "abilityIcon": "spell_shadow_haunting.jpg"}}, {"timestamp": 8325792, "type": "removedebuff", "sourceID": 32, "sourceIsFriendly": true, "targetID": 55, "targetIsFriendly": false, "ability": {"name": "Taunt", "guid": 355, "type": 1, "abilityIcon": "spell_nature_reincarnation.jpg"}}, {"timestamp": 8326409, "type": "refreshdebuff", "sourceID": 15, "sourceIsFriendly": true, "targetID": 55, "targetIsFriendly": false, "ability": {"name": "Mind Flay", "guid": 18807, "type": 32, "abilityIcon": "spell_shadow_siphonmana.jpg"}}, {"timestamp": 8326814, "type": "removedebuff", "sourceID": 14, "sourceIsFriendly": true, "targetID": 55, "targetIsFriendly": false, "ability": {"name": "Curse of the Elements", "guid": 11722, "type": 32, "abilityIcon": "spell_shadow_chilltouch.jpg"}}, {"timestamp": 8326814, "type": "removedebuff", "sourceID": 15, "sourceIsFriendly": true, "targetID": 55, "targetIsFriendly": false, "ability": {"name": "Vampiric Embrace", "guid": 15286, "type": 32, "abilityIcon": "spell_shadow_unsummonbuilding.jpg"}}, {"timestamp": 8326814, "type": "removedebuff", "sourceID": 23, "sourceIsFriendly": true, "targetID": 55, "targetIsFriendly": false, "ability": {"name": "Curse of Shadow", "guid": 17937, "type": 32, "abilityIcon": "spell_shadow_curseofachimonde.jpg"}}, {"timestamp": 8326814, "type": "removedebuff", "sourceID": 33, "sourceIsFriendly": true, "targetID": 55, "targetIsFriendly": false, "ability": {"name": "Sunder Armor", "guid": 11597, "type": 1, "abilityIcon": "ability_warrior_sunder.jpg"}}, {"timestamp": 8326814, "type": "removedebuff", "sourceID": 15, "sourceIsFriendly": true, "targetID": 55, "targetIsFriendly": false, "ability": {"name": "Mind Flay", "guid": 18807, "type": 32, "abilityIcon": "spell_shadow_siphonmana.jpg"}}, {"timestamp": 8326814, "type": "removedebuff", "sourceID": 15, "sourceIsFriendly": true, "targetID": 55, "targetIsFriendly": false, "ability": {"name": "Shadow Word: Pain", "guid": 10894, "type": 32, "abilityIcon": "spell_shadow_shadowwordpain.jpg"}}, {"timestamp": 8326814, "type": "removedebuff", "sourceID": 15, "sourceIsFriendly": true, "targetID": 55, "targetIsFriendly": false, "ability": {"name": "", "guid": 15258, "type": 32, "abilityIcon": "spell_shadow_blackplague.jpg"}}, {"timestamp": 8326814, "type": "removedebuff", "sourceID": 23, "sourceIsFriendly": true, "targetID": 55, "targetIsFriendly": false, "ability": {"name": "Corruption", "guid": 11672, "type": 32, "abilityIcon": "spell_shadow_abominationexplosion.jpg"}}, {"timestamp": 8326814, "type": "removedebuff", "sourceID": 27, "sourceIsFriendly": true, "targetID": 55, "targetIsFriendly": false, "ability": {"name": "Curse of Recklessness", "guid": 11717, "type": 32, "abilityIcon": "spell_shadow_unholystrength.jpg"}}, {"timestamp": 8326814, "type": "removedebuff", "sourceID": 18, "sourceIsFriendly": true, "targetID": 55, "targetIsFriendly": false, "ability": {"name": "Moonfire", "guid": 9834, "type": 64, "abilityIcon": "spell_nature_starfall.jpg"}}, {"timestamp": 8326814, "type": "removedebuff", "sourceID": 7, "sourceIsFriendly": true, "targetID": 55, "targetIsFriendly": false, "ability": {"name": "", "guid": 12579, "type": 16, "abilityIcon": "spell_frost_chillingblast.jpg"}}]}